qepy-7.2.0.dist-info/RECORD
qepy-7.2.0.dist-info/WHEEL
qepy-7.2.0.dist-info/top_level.txt
qepy-7.2.0.dist-info/METADATA
qepy/qebins.py
qepy/io.py
qepy/__init__.py
qepy/core.py
qepy/__config__.py
qepy/mpi.py
qepy/calculator.py
qepy/driver.py
qepy/__main__.py
qepy/.dylibs/libgfortran.5.dylib
qepy/.dylibs/libquadmath.0.dylib
qepy/.dylibs/libgcc_s.1.1.dylib
qepy/qepylibs/libqepy_phonon_ph.so
qepy/qepylibs/libqepy_mbd.so
qepy/qepylibs/libqepy_utilxlib.so
qepy/qepylibs/libqepy_neb.so
qepy/qepylibs/libqepy_dft_d3.so
qepy/qepylibs/libqepy_gww_pw4gww.so
qepy/qepylibs/libqepy_phonon_gamma.so
qepy/qepylibs/libqepy_tddfpt.so
qepy/qepylibs/libqepy_kcw.so
qepy/qepylibs/libqepy_atomic.so
qepy/qepylibs/libqepy_gww_head.so
qepy/qepylibs/libqepy_gww_simple.so
qepy/qepylibs/libqepy_xspectra.so
qepy/qepylibs/libqepy_hp.so
qepy/qepylibs/__init__.py
qepy/qepylibs/libqepy_lr_modules.so
qepy/qepylibs/libqepy_pw.so
qepy/qepylibs/libqepy_fftxlib.so
qepy/qepylibs/libqepy_gww_gww.so
qepy/qepylibs/libqepy_pp.so
qepy/qepylibs/libqepy_kcw_pp.so
qepy/qepylibs/libqepy_laxlib.so
qepy/qepylibs/libqepy_ks_solvers.so
qepy/qepylibs/libqepy_gww_simple_ip.so
qepy/qepylibs/libqepy_gww_simple_bse.so
qepy/qepylibs/libqepy_cpv.so
qepy/qepylibs/libqepy_gww_bse.so
qepy/qepylibs/libqepy_xclib.so
qepy/qepylibs/libqepy_cetddft.so
qepy/qepylibs/libqepy_pwcond.so
qepy/qepylibs/libqepy_modules.so
qepy/qepylibs/libqepy_upflib.so
qepy/qepylibs/libqepy_gww_minpack.so
qepy/qepylibs/qepy_gww_pw4gww/io_base_export.py
qepy/qepylibs/qepy_gww_pw4gww/__init__.py
qepy/qepylibs/qepy_pw/basis.py
qepy/qepylibs/qepy_pw/qepy_common.py
qepy/qepylibs/qepy_pw/rap_point_group.py
qepy/qepylibs/qepy_pw/ener.py
qepy/qepylibs/qepy_pw/fixed_occ.py
qepy/qepylibs/qepy_pw/fft_types.py
qepy/qepylibs/qepy_pw/wvfct.py
qepy/qepylibs/qepy_pw/rap_point_group_is.py
qepy/qepylibs/qepy_pw/__init__.py
qepy/qepylibs/qepy_pw/qepy_mod.py
qepy/qepylibs/qepy_pw/symme.py
qepy/qepylibs/qepy_pw/rap_point_group_so.py
qepy/qepylibs/qepy_pw/relax.py
qepy/qepylibs/qepy_pw/scf.py
qepy/qepylibs/qepy_pw/pwcom.py
