Metadata-Version: 2.1
Name: qepy
Version: 7.2.0
Summary: QEpy: Quantum ESPRESSO Python interface
Author-email: Michele Pavanello <m.pavanello@rutgers.edu>, Xuecheng Shao <shaoxc@jlu.edu.cn>
Maintainer-email: Michele Pavanello <m.pavanello@rutgers.edu>, Xuecheng Shao <shaoxc@jlu.edu.cn>
License: 		    GNU GENERAL PUBLIC LICENSE
Project-URL: homepage, https://gitlab.com/shaoxc/qepy
Project-URL: documentation, http://qepy.rutgers.edu
Project-URL: source, https://gitlab.com/shaoxc/qepy
Classifier: Development Status :: 3 - Alpha
Classifier: Intended Audience :: Science/Research
Classifier: Programming Language :: Python :: 3
Classifier: Programming Language :: Python :: 3.8
Classifier: Programming Language :: Python :: 3.9
Classifier: Programming Language :: Python :: 3.10
Classifier: Programming Language :: Python :: 3.11
Classifier: Programming Language :: Python :: 3.12
Classifier: Topic :: Scientific/Engineering :: Chemistry
Classifier: Topic :: Scientific/Engineering :: Physics
Classifier: Operating System :: POSIX
Classifier: Operating System :: Unix
Classifier: Operating System :: MacOS
Requires-Python: >=3.8
Requires-Dist: f90wrap>=0.2.14
Requires-Dist: numpy<2.0
Provides-Extra: docs
Requires-Dist: sphinx; extra == "docs"
Requires-Dist: sphinx-rtd-theme>=2.0.0; extra == "docs"
Requires-Dist: sphinx-panels; extra == "docs"
Requires-Dist: sphinx-copybutton; extra == "docs"
Requires-Dist: sphinx-inline-tabs; extra == "docs"
Requires-Dist: nbsphinx; extra == "docs"
Requires-Dist: pandoc; extra == "docs"
Provides-Extra: test
Requires-Dist: pytest; extra == "test"
Requires-Dist: pytest-cov; extra == "test"
Requires-Dist: pytest-mpi; extra == "test"
Requires-Dist: ase; extra == "test"
Provides-Extra: all
Requires-Dist: mpi4py; extra == "all"
Requires-Dist: dftpy; extra == "all"
